{
	"salomlashuv": ["salom", "hello", "salomlar", "qq", "salam", "oooooooooooooo salomla"],
	"hol ahvol": ["qalaysiz", "qandesiz", "yaxshimisiz", "ahvolingiz qandey", "Qales broooo", "nima gapla"],
	"savol": [
		"nima",
		"kim",
		"qayerda",
		"qachon",
		"boladimi",
		"munkinmi",
		"sevaszmi",
		"kimla bor",
		"1ta sen bomisan",
		"?",
		"Janr?"
	],
	"javob": ["Men bor", "Hech kim yoq", "ha", "yoq"],
	"tabrik": ["tabriklayman", "tabriklimiz", "tabrik", "tug'ilgan kuningiz bilan"],
	"vaqt": ["ertaga", "bugun", "kecha", "tongda", "20:30", "keyinroq", "20:00", "1540 yil"],
	"ism": ["muslima"],
	"sokinish": ["dalbayop", "yeban"],
	"iltimos": [
		"super kuchlarni chiqaringlar",
		"Lic oting bir gapm bor",
		"Akalar birorta yaxshiro kino aytvorila korgani iltimos"
	],
	"boshqa": ["", " ", "chungan chundi", "Ahh joningdan", "Man uni etmadim chiqarish mayapdiki", "alyu", "!p 2b2t.uz"]
}
